{"is_source_file": true, "format": "JavaScript", "description": "This is an entry point for a React application, setting up the root rendering of the main App component.", "external_files": ["./index.css", "./App"], "external_methods": ["ReactDOM.createRoot", "root.render"], "published": [], "classes": [], "methods": [{"name": "ReactDOM.createRoot", "description": "Creates a root React DOM container for rendering React components."}, {"name": "root.render", "description": "Renders React elements into the root DOM container."}], "calls": ["ReactDOM.createRoot", "root.render"], "search-terms": ["React", "ReactDOM", "index.js", "main entry", "render", "root", "App component"], "state": 2, "file_id": 6, "knowledge_revision": 22, "git_revision": "a3427937c9897cd129cd7083becc2db55571d3f7", "ctags": [{"_type": "tag", "name": "root", "path": "/home/kavia/workspace/code-generation/simple-task-organizer-18634-18643/to_do_frontend/src/index.js", "pattern": "/^const root = ReactDOM.createRoot(document.getElementById('root'));$/", "language": "JavaScript", "kind": "constant"}], "hash": "9fc5841375336fc175b49f8767a11383", "format-version": 4, "code-base-name": "to_do_frontend", "filename": "to_do_frontend/src/index.js", "revision_history": [{"22": "a3427937c9897cd129cd7083becc2db55571d3f7"}]}